deepml/__init__.py
deepml/constants.py
deepml/datasets.py
deepml/losses.py
deepml/tasks.py
deepml/train.py
deepml/transforms.py
deepml/utils.py
deepml/visualize.py
deepml/geospatial/__init__.py
deepml/geospatial/utils.py
deepml/metrics/__init__.py
deepml/metrics/classification.py
deepml/metrics/commons.py
deepml/metrics/segmentation.py
deepml/models/__init__.py
deepml/models/refine_net.py
deepml/models/unet.py
deepml/resources/fonts/OpenSans-Light.ttf
deepml-2.0.0.dist-info/LICENSE
deepml-2.0.0.dist-info/METADATA
deepml-2.0.0.dist-info/WHEEL
deepml-2.0.0.dist-info/top_level.txt
deepml-2.0.0.dist-info/RECORD
