Metadata-Version: 2.1
Name: deepml
Version: 2.0.0
Summary: Library for training deep neural nets in Pytorch.
Home-page: https://github.com/sagar-rathod/PytorchDeepML
Author: Sagar Rathod
Author-email: sagar100rathod@gmail.com
License: UNKNOWN
Platform: UNKNOWN
Classifier: Development Status :: 5 - Production/Stable
Classifier: Programming Language :: Python :: 3.6
Classifier: Programming Language :: Python :: 3.7
Classifier: Programming Language :: Python :: 3.8
Classifier: License :: OSI Approved :: MIT License
Classifier: License :: Free For Educational Use
Classifier: Operating System :: OS Independent
Classifier: Intended Audience :: Developers
Classifier: Intended Audience :: Science/Research
Classifier: Topic :: Software Development :: Libraries
Classifier: Topic :: Software Development :: Libraries :: Python Modules
Requires-Python: >=3.6
Requires-Dist: tensorboard (>=1.14.0)
Requires-Dist: scikit-learn (>=0.22)
Requires-Dist: numpy (>=1.16)
Requires-Dist: pandas (>=0.25.3)
Requires-Dist: matplotlib (>=2.2.5)
